llama_index/utils/azure/__init__.py
llama_index/utils/azure/table.py
llama_index_utils_azure-0.4.1.dist-info/METADATA
llama_index_utils_azure-0.4.1.dist-info/WHEEL
llama_index_utils_azure-0.4.1.dist-info/licenses/LICENSE
llama_index_utils_azure-0.4.1.dist-info/RECORD
