Metadata-Version: 2.4
Name: llama-index-utils-azure
Version: 0.4.1
Summary: llama-index utils azure
Author-email: Fran Aguilera <falven2000@hotmail.com>
Maintainer: falven
License-Expression: MIT
License-File: LICENSE
Keywords: azure,utils
Requires-Python: <4.0,>=3.9
Requires-Dist: llama-index-core<0.15,>=0.13.0
